PyAltiumRun/AltiumRun.py
PyAltiumRun/__init__.py
PyAltiumRun/py.typed
PyAltiumRun/helpers/AltiumHelper.py
PyAltiumRun/helpers/__init__.py
PyAltiumRun/scriptingbase/__init__.py
PyAltiumRun/scriptingbase/logger.pas
PyAltiumRun/scriptingbase/main.pas
PyAltiumRun-0.1.4.dist-info/LICENSE
PyAltiumRun-0.1.4.dist-info/METADATA
PyAltiumRun-0.1.4.dist-info/WHEEL
PyAltiumRun-0.1.4.dist-info/top_level.txt
PyAltiumRun-0.1.4.dist-info/RECORD
